[
  { "province_name": "กรุงเทพมหานคร" },
  { "province_name": "สมุทรปราการ" },
  { "province_name": "นนทบุรี" },
  { "province_name": "ปทุมธานี" },
  { "province_name": "พระนครศรีอยุธยา" },
  { "province_name": "อ่างทอง" },
  { "province_name": "ลพบุรี" },
  { "province_name": "สิงห์บุรี" },
  { "province_name": "ชัยนาท" },
  { "province_name": "สระบุรี" },
  { "province_name": "ชลบุรี" },
  { "province_name": "ระยอง" },
  { "province_name": "จันทบุรี" },
  { "province_name": "ตราด" },
  { "province_name": "ฉะเชิงเทรา" },
  { "province_name": "ปราจีนบุรี" },
  { "province_name": "นครนายก" },
  { "province_name": "สระแก้ว" },
  { "province_name": "นครราชสีมา" },
  { "province_name": "บุรีรัมย์" },
  { "province_name": "สุรินทร์" },
  { "province_name": "ศรีสะเกษ" },
  { "province_name": "อุบลราชธานี" },
  { "province_name": "ยโสธร" },
  { "province_name": "ชัยภูมิ" },
  { "province_name": "อำนาจเจริญ" },
  { "province_name": "หนองบัวลำภู" },
  { "province_name": "ขอนแก่น" },
  { "province_name": "อุดรธานี" },
  { "province_name": "เลย" },
  { "province_name": "หนองคาย" },
  { "province_name": "มหาสารคาม" },
  { "province_name": "ร้อยเอ็ด" },
  { "province_name": "กาฬสินธุ์" },
  { "province_name": "สกลนคร" },
  { "province_name": "นครพนม" },
  { "province_name": "มุกดาหาร" },
  { "province_name": "เชียงใหม่" },
  { "province_name": "ลำพูน" },
  { "province_name": "ลำปาง" },
  { "province_name": "อุตรดิตถ์" },
  { "province_name": "แพร่" },
  { "province_name": "น่าน" },
  { "province_name": "พะเยา" },
  { "province_name": "เชียงราย" },
  { "province_name": "แม่ฮ่องสอน" },
  { "province_name": "นครสวรรค์" },
  { "province_name": "อุทัยธานี" },
  { "province_name": "กำแพงเพชร" },
  { "province_name": "ตาก" },
  { "province_name": "สุโขทัย" },
  { "province_name": "พิษณุโลก" },
  { "province_name": "พิจิตร" },
  { "province_name": "เพชรบูรณ์" },
  { "province_name": "ราชบุรี" },
  { "province_name": "กาญจนบุรี" },
  { "province_name": "สุพรรณบุรี" },
  { "province_name": "นครปฐม" },
  { "province_name": "สมุทรสาคร" },
  { "province_name": "สมุทรสงคราม" },
  { "province_name": "เพชรบุรี" },
  { "province_name": "ประจวบคีรีขันธ์" },
  { "province_name": "นครศรีธรรมราช" },
  { "province_name": "กระบี่" },
  { "province_name": "พังงา" },
  { "province_name": "ภูเก็ต" },
  { "province_name": "สุราษฎร์ธานี" },
  { "province_name": "ระนอง" },
  { "province_name": "ชุมพร" },
  { "province_name": "สงขลา" },
  { "province_name": "สตูล" },
  { "province_name": "ตรัง" },
  { "province_name": "พัทลุง" },
  { "province_name": "ปัตตานี" },
  { "province_name": "ยะลา" },
  { "province_name": "นราธิวาส" },
  { "province_name": "บึงกาฬ" }
]
